{
  "input": "9.jpg",
  "size_hw": [
    1200,
    675
  ],
  "color_stats": [
    {
      "space": "RGB",
      "mean": [
        122.50395555555555,
        110.38417901234568,
        107.59570987654321
      ],
      "std": [
        51.981131469000765,
        53.51151042963972,
        54.58498866690944
      ]
    },
    {
      "space": "HSV",
      "mean": [
        33.83814074074074,
        44.24788518518518,
        123.79175802469136
      ],
      "std": [
        52.46845395889057,
        31.36151787703452,
        52.81887338724773
      ]
    },
    {
      "space": "Lab",
      "mean": [
        119.34843580246914,
        132.4612148148148,
        131.51436172839507
      ],
      "std": [
        54.426991612148306,
        4.554406023623017,
        3.442528666155208
      ]
    }
  ],
  "dominant_colors": [
    {
      "share": 0.22829506172839506,
      "BGR": [
        104,
        107,
        121
      ],
      "RGB": [
        121,
        107,
        104
      ],
      "HSV": [
        5,
        36,
        121
      ],
      "Lab": [
        119,
        133,
        132
      ]
    },
    {
      "share": 0.22663703703703703,
      "BGR": [
        69,
        72,
        86
      ],
      "RGB": [
        86,
        72,
        69
      ],
      "HSV": [
        5,
        50,
        86
      ],
      "Lab": [
        82,
        133,
        132
      ]
    },
    {
      "share": 0.2094753086419753,
      "BGR": [
        142,
        145,
        162
      ],
      "RGB": [
        162,
        145,
        142
      ],
      "HSV": [
        5,
        31,
        162
      ],
      "Lab": [
        157,
        134,
        132
      ]
    },
    {
      "share": 0.17151111111111111,
      "BGR": [
        34,
        38,
        48
      ],
      "RGB": [
        48,
        38,
        34
      ],
      "HSV": [
        9,
        74,
        48
      ],
      "Lab": [
        42,
        131,
        133
      ]
    },
    {
      "share": 0.1640814814814815,
      "BGR": [
        196,
        196,
        199
      ],
      "RGB": [
        199,
        196,
        196
      ],
      "HSV": [
        0,
        4,
        199
      ],
      "Lab": [
        203,
        129,
        128
      ]
    }
  ],
  "heuristics": {
    "rustish_ratio": 0.08672222222222223,
    "zincish_ratio": 0.015598765432098765,
    "a_median": 132.0,
    "b_median": 132.0,
    "a_thresh": 138.0,
    "b_thresh": 138.0
  },
  "palette_image": "color_out\\9_palette.png"
}